dmchat/__init__.py
dmchat-0.1.0.dist-info/LICENSE
dmchat-0.1.0.dist-info/METADATA
dmchat-0.1.0.dist-info/WHEEL
dmchat-0.1.0.dist-info/top_level.txt
dmchat-0.1.0.dist-info/RECORD
